{
  "level": 22,
  "timeLimit": 332,
  "cols": 3,
  "rows": 4,
  "cellCap": 3,
  "goods": [
    "air_freshener",
    "berry_smoothie",
    "butter_box",
    "cereal_choco",
    "cream_cheese",
    "grapes",
    "gum_pack",
    "jelly_bag",
    "paint_can",
    "sandwich_cookies",
    "seaweed_snack",
    "soda",
    "tea_box",
    "toaster_pastry"
  ],
  "combo": {
    "resetAfterMs": 20000
  },
  "scoring": {
    "starsPerSort": 1,
    "comboBonus": 1
  },
  "_gen": {
    "distinct": 14,
    "depthRange": [
      2,
      3
    ],
    "emptyCubbies": 1,
    "frontGaps": 6,
    "lockCubbies": 2,
    "totalGoods": 72,
    "attempt": 5
  },
  "cubbies": [
    {
      "r": 0,
      "c": 0,
      "layers": [
        [
          null,
          null,
          null
        ]
      ]
    },
    {
      "r": 0,
      "c": 1,
      "layers": [
        [
          "grapes",
          "grapes",
          "cereal_choco"
        ],
        [
          "cream_cheese",
          "cream_cheese",
          "berry_smoothie"
        ],
        [
          "gum_pack",
          "jelly_bag",
          "berry_smoothie"
        ]
      ]
    },
    {
      "r": 0,
      "c": 2,
      "lock": 3,
      "layers": [
        [
          "tea_box",
          null,
          "gum_pack"
        ],
        [
          "cream_cheese",
          "cereal_choco",
          "paint_can"
        ]
      ]
    },
    {
      "r": 1,
      "c": 0,
      "layers": [
        [
          null,
          "gum_pack",
          "sandwich_cookies"
        ],
        [
          "butter_box",
          "cream_cheese",
          "toaster_pastry"
        ]
      ]
    },
    {
      "r": 1,
      "c": 1,
      "layers": [
        [
          "butter_box",
          "butter_box",
          "cereal_choco"
        ],
        [
          "grapes",
          "air_freshener",
          "seaweed_snack"
        ]
      ]
    },
    {
      "r": 1,
      "c": 2,
      "layers": [
        [
          "sandwich_cookies",
          "gum_pack",
          "sandwich_cookies"
        ],
        [
          "gum_pack",
          "air_freshener",
          "air_freshener"
        ]
      ]
    },
    {
      "r": 2,
      "c": 0,
      "lock": 3,
      "layers": [
        [
          "berry_smoothie",
          "jelly_bag",
          "soda"
        ],
        [
          "grapes",
          "butter_box",
          "berry_smoothie"
        ],
        [
          "jelly_bag",
          "seaweed_snack",
          "air_freshener"
        ]
      ]
    },
    {
      "r": 2,
      "c": 1,
      "layers": [
        [
          "soda",
          "sandwich_cookies",
          "gum_pack"
        ],
        [
          "paint_can",
          "cream_cheese",
          "butter_box"
        ],
        [
          "cereal_choco",
          "grapes",
          "berry_smoothie"
        ]
      ]
    },
    {
      "r": 2,
      "c": 2,
      "layers": [
        [
          "air_freshener",
          null,
          null
        ],
        [
          "toaster_pastry",
          "paint_can",
          "paint_can"
        ]
      ]
    },
    {
      "r": 3,
      "c": 0,
      "layers": [
        [
          "grapes",
          "air_freshener",
          "sandwich_cookies"
        ],
        [
          "paint_can",
          "cream_cheese",
          "paint_can"
        ],
        [
          "cereal_choco",
          "tea_box",
          "toaster_pastry"
        ]
      ]
    },
    {
      "r": 3,
      "c": 1,
      "layers": [
        [
          "berry_smoothie",
          null,
          "toaster_pastry"
        ],
        [
          "toaster_pastry",
          "sandwich_cookies",
          "cereal_choco"
        ]
      ]
    },
    {
      "r": 3,
      "c": 2,
      "layers": [
        [
          null,
          "toaster_pastry",
          "butter_box"
        ],
        [
          "tea_box",
          "soda",
          "seaweed_snack"
        ]
      ]
    }
  ]
}
