{
  "level": 93,
  "timeLimit": 240,
  "cols": 4,
  "rows": 5,
  "cellCap": 3,
  "goods": [
    "butter",
    "cake_slice",
    "cereal_box",
    "cola",
    "corn_cob",
    "donut_pink",
    "gravy_boat",
    "icecream_cone",
    "koala_toy",
    "owl_toy",
    "pancake_stack",
    "pear",
    "popcorn_bag",
    "shampoo",
    "teapot"
  ],
  "combo": {
    "resetAfterMs": 20000
  },
  "scoring": {
    "starsPerSort": 1,
    "comboBonus": 1
  },
  "_gen": {
    "distinct": 15,
    "depthRange": [
      4,
      5
    ],
    "workspaces": 4,
    "lockCubbies": 7,
    "totalGoods": 210,
    "attempt": 66
  },
  "cubbies": [
    {
      "r": 0,
      "c": 0,
      "lock": 3,
      "layers": [
        [
          "donut_pink",
          "gravy_boat",
          "corn_cob"
        ],
        [
          "icecream_cone",
          "pancake_stack",
          "cola"
        ],
        [
          "koala_toy",
          "butter",
          "cereal_box"
        ],
        [
          "icecream_cone",
          "popcorn_bag",
          "cereal_box"
        ]
      ]
    },
    {
      "r": 0,
      "c": 1,
      "layers": [
        [
          "teapot",
          "popcorn_bag",
          "pear"
        ],
        [
          "shampoo",
          "butter",
          "butter"
        ],
        [
          "pear",
          "cake_slice",
          "cereal_box"
        ],
        [
          "icecream_cone",
          "gravy_boat",
          "pancake_stack"
        ]
      ]
    },
    {
      "r": 0,
      "c": 2,
      "layers": [
        [
          "cereal_box",
          "butter",
          "koala_toy"
        ],
        [
          "gravy_boat",
          "cola",
          "butter"
        ],
        [
          "cola",
          "icecream_cone",
          "koala_toy"
        ],
        [
          "teapot",
          "cake_slice",
          "shampoo"
        ]
      ]
    },
    {
      "r": 0,
      "c": 3,
      "layers": [
        [
          "cereal_box",
          "pear",
          "cola"
        ],
        [
          "koala_toy",
          "owl_toy",
          "cake_slice"
        ],
        [
          "gravy_boat",
          "corn_cob",
          "donut_pink"
        ],
        [
          "shampoo",
          "corn_cob",
          "koala_toy"
        ],
        [
          "icecream_cone",
          "pancake_stack",
          "owl_toy"
        ]
      ]
    },
    {
      "r": 1,
      "c": 0,
      "lock": 5,
      "layers": [
        [
          "corn_cob",
          "owl_toy",
          "cake_slice"
        ],
        [
          "teapot",
          "gravy_boat",
          "butter"
        ],
        [
          "pear",
          "corn_cob",
          "teapot"
        ],
        [
          "cola",
          "butter",
          "icecream_cone"
        ],
        [
          "butter",
          "pancake_stack",
          "cake_slice"
        ]
      ]
    },
    {
      "r": 1,
      "c": 1,
      "layers": [
        [
          "koala_toy",
          "owl_toy",
          "gravy_boat"
        ],
        [
          "pear",
          "icecream_cone",
          "butter"
        ],
        [
          "popcorn_bag",
          "pear",
          "cake_slice"
        ],
        [
          "gravy_boat",
          "shampoo",
          "donut_pink"
        ],
        [
          "donut_pink",
          "koala_toy",
          "cola"
        ]
      ]
    },
    {
      "r": 1,
      "c": 2,
      "lock": 1,
      "layers": [
        [
          "corn_cob",
          "cereal_box",
          "icecream_cone"
        ],
        [
          "pear",
          "owl_toy",
          "shampoo"
        ],
        [
          "butter",
          "butter",
          "popcorn_bag"
        ],
        [
          "corn_cob",
          "teapot",
          "teapot"
        ]
      ]
    },
    {
      "r": 1,
      "c": 3,
      "lock": 2,
      "layers": [
        [
          "pear",
          "koala_toy",
          "popcorn_bag"
        ],
        [
          "cereal_box",
          "icecream_cone",
          "koala_toy"
        ],
        [
          "shampoo",
          "donut_pink",
          "pancake_stack"
        ],
        [
          "popcorn_bag",
          "corn_cob",
          "koala_toy"
        ]
      ]
    },
    {
      "r": 2,
      "c": 0,
      "lock": 1,
      "layers": [
        [
          "gravy_boat",
          "teapot",
          "popcorn_bag"
        ],
        [
          "shampoo",
          "gravy_boat",
          "butter"
        ],
        [
          "cake_slice",
          "cake_slice",
          "corn_cob"
        ],
        [
          "koala_toy",
          "donut_pink",
          "corn_cob"
        ]
      ]
    },
    {
      "r": 2,
      "c": 1,
      "layers": [
        [
          null,
          null,
          null
        ]
      ]
    },
    {
      "r": 2,
      "c": 2,
      "layers": [
        [
          null,
          null,
          null
        ]
      ]
    },
    {
      "r": 2,
      "c": 3,
      "lock": 3,
      "layers": [
        [
          "teapot",
          "pancake_stack",
          "donut_pink"
        ],
        [
          "donut_pink",
          "popcorn_bag",
          "pancake_stack"
        ],
        [
          "donut_pink",
          "cake_slice",
          "shampoo"
        ],
        [
          "cake_slice",
          "cola",
          "shampoo"
        ],
        [
          "butter",
          "owl_toy",
          "pancake_stack"
        ]
      ]
    },
    {
      "r": 3,
      "c": 0,
      "lock": 4,
      "layers": [
        [
          "gravy_boat",
          "cola",
          "gravy_boat"
        ],
        [
          "koala_toy",
          "cola",
          "shampoo"
        ],
        [
          "teapot",
          "donut_pink",
          "cola"
        ],
        [
          "koala_toy",
          "shampoo",
          "gravy_boat"
        ]
      ]
    },
    {
      "r": 3,
      "c": 1,
      "layers": [
        [
          "corn_cob",
          "koala_toy",
          "icecream_cone"
        ],
        [
          "owl_toy",
          "popcorn_bag",
          "icecream_cone"
        ],
        [
          "shampoo",
          "teapot",
          "pancake_stack"
        ],
        [
          "corn_cob",
          "shampoo",
          "icecream_cone"
        ],
        [
          "cake_slice",
          "pancake_stack",
          "pancake_stack"
        ]
      ]
    },
    {
      "r": 3,
      "c": 2,
      "layers": [
        [
          "pear",
          "cola",
          "pancake_stack"
        ],
        [
          "teapot",
          "pear",
          "pear"
        ],
        [
          "owl_toy",
          "popcorn_bag",
          "cake_slice"
        ],
        [
          "cereal_box",
          "cake_slice",
          "shampoo"
        ],
        [
          "cola",
          "pancake_stack",
          "pancake_stack"
        ]
      ]
    },
    {
      "r": 3,
      "c": 3,
      "layers": [
        [
          null,
          null,
          null
        ]
      ]
    },
    {
      "r": 4,
      "c": 0,
      "layers": [
        [
          "cereal_box",
          "teapot",
          "shampoo"
        ],
        [
          "gravy_boat",
          "butter",
          "cake_slice"
        ],
        [
          "pancake_stack",
          "popcorn_bag",
          "cola"
        ],
        [
          "butter",
          "popcorn_bag",
          "icecream_cone"
        ]
      ]
    },
    {
      "r": 4,
      "c": 1,
      "layers": [
        [
          "popcorn_bag",
          "koala_toy",
          "cereal_box"
        ],
        [
          "owl_toy",
          "corn_cob",
          "gravy_boat"
        ],
        [
          "icecream_cone",
          "corn_cob",
          "corn_cob"
        ],
        [
          "owl_toy",
          "donut_pink",
          "owl_toy"
        ]
      ]
    },
    {
      "r": 4,
      "c": 2,
      "layers": [
        [
          null,
          null,
          null
        ]
      ]
    },
    {
      "r": 4,
      "c": 3,
      "layers": [
        [
          "cereal_box",
          "gravy_boat",
          "cola"
        ],
        [
          "pear",
          "cake_slice",
          "cola"
        ],
        [
          "icecream_cone",
          "cereal_box",
          "owl_toy"
        ],
        [
          "popcorn_bag",
          "donut_pink",
          "popcorn_bag"
        ]
      ]
    }
  ]
}
