{
  "level": 61,
  "timeLimit": 290,
  "cols": 3,
  "rows": 5,
  "cellCap": 3,
  "goods": [
    "bee_toy",
    "broccoli",
    "butter_tub",
    "chocolate_tablet",
    "cracker_box",
    "cupcake_tray",
    "green_beans",
    "juice_6pack",
    "milk_carton_tall",
    "owl_toy",
    "pomegranate",
    "popsicle_twin",
    "pumpkin",
    "red_onion"
  ],
  "combo": {
    "resetAfterMs": 20000
  },
  "scoring": {
    "starsPerSort": 1,
    "comboBonus": 1
  },
  "_gen": {
    "distinct": 14,
    "depthRange": [
      3,
      5
    ],
    "emptyCubbies": 1,
    "frontGaps": 6,
    "lockCubbies": 5,
    "totalGoods": 150,
    "attempt": 3
  },
  "cubbies": [
    {
      "r": 0,
      "c": 0,
      "layers": [
        [
          "cracker_box",
          "broccoli",
          null
        ],
        [
          "bee_toy",
          "cracker_box",
          "pomegranate"
        ],
        [
          "green_beans",
          "owl_toy",
          "red_onion"
        ]
      ]
    },
    {
      "r": 0,
      "c": 1,
      "layers": [
        [
          "butter_tub",
          "cracker_box",
          "cracker_box"
        ],
        [
          "cupcake_tray",
          "milk_carton_tall",
          "green_beans"
        ],
        [
          "cupcake_tray",
          "red_onion",
          "popsicle_twin"
        ]
      ]
    },
    {
      "r": 0,
      "c": 2,
      "layers": [
        [
          "popsicle_twin",
          "cracker_box",
          null
        ],
        [
          "cracker_box",
          "cupcake_tray",
          "chocolate_tablet"
        ],
        [
          "juice_6pack",
          "cracker_box",
          "pomegranate"
        ],
        [
          "butter_tub",
          "chocolate_tablet",
          "milk_carton_tall"
        ]
      ]
    },
    {
      "r": 1,
      "c": 0,
      "layers": [
        [
          "popsicle_twin",
          "juice_6pack",
          "juice_6pack"
        ],
        [
          "milk_carton_tall",
          "green_beans",
          "butter_tub"
        ],
        [
          "butter_tub",
          "cupcake_tray",
          "red_onion"
        ],
        [
          "pumpkin",
          "cupcake_tray",
          "pumpkin"
        ]
      ]
    },
    {
      "r": 1,
      "c": 1,
      "layers": [
        [
          "chocolate_tablet",
          null,
          "owl_toy"
        ],
        [
          "popsicle_twin",
          "pomegranate",
          "butter_tub"
        ],
        [
          "milk_carton_tall",
          "butter_tub",
          "chocolate_tablet"
        ],
        [
          "cupcake_tray",
          "chocolate_tablet",
          "green_beans"
        ]
      ]
    },
    {
      "r": 1,
      "c": 2,
      "lock": 2,
      "layers": [
        [
          "popsicle_twin",
          "green_beans",
          "milk_carton_tall"
        ],
        [
          "butter_tub",
          "pumpkin",
          "cupcake_tray"
        ],
        [
          "cupcake_tray",
          "milk_carton_tall",
          "milk_carton_tall"
        ],
        [
          "butter_tub",
          "pomegranate",
          "green_beans"
        ],
        [
          "milk_carton_tall",
          "popsicle_twin",
          "popsicle_twin"
        ]
      ]
    },
    {
      "r": 2,
      "c": 0,
      "lock": 3,
      "layers": [
        [
          "butter_tub",
          "broccoli",
          "butter_tub"
        ],
        [
          "bee_toy",
          "red_onion",
          "milk_carton_tall"
        ],
        [
          "red_onion",
          "cupcake_tray",
          "owl_toy"
        ],
        [
          "bee_toy",
          "owl_toy",
          "broccoli"
        ],
        [
          "cupcake_tray",
          "broccoli",
          "milk_carton_tall"
        ]
      ]
    },
    {
      "r": 2,
      "c": 1,
      "layers": [
        [
          "juice_6pack",
          null,
          "juice_6pack"
        ],
        [
          "pumpkin",
          "bee_toy",
          "bee_toy"
        ],
        [
          "broccoli",
          "broccoli",
          "pomegranate"
        ]
      ]
    },
    {
      "r": 2,
      "c": 2,
      "layers": [
        [
          "red_onion",
          "butter_tub",
          "bee_toy"
        ],
        [
          "broccoli",
          "butter_tub",
          "pumpkin"
        ],
        [
          "pomegranate",
          "owl_toy",
          "popsicle_twin"
        ],
        [
          "green_beans",
          "broccoli",
          "cupcake_tray"
        ],
        [
          "popsicle_twin",
          "green_beans",
          "popsicle_twin"
        ]
      ]
    },
    {
      "r": 3,
      "c": 0,
      "layers": [
        [
          null,
          null,
          null
        ]
      ]
    },
    {
      "r": 3,
      "c": 1,
      "layers": [
        [
          "red_onion",
          "cracker_box",
          "pumpkin"
        ],
        [
          "milk_carton_tall",
          "pomegranate",
          "owl_toy"
        ],
        [
          "green_beans",
          "bee_toy",
          "green_beans"
        ]
      ]
    },
    {
      "r": 3,
      "c": 2,
      "lock": 1,
      "layers": [
        [
          null,
          "popsicle_twin",
          "chocolate_tablet"
        ],
        [
          "broccoli",
          "owl_toy",
          "pumpkin"
        ],
        [
          "juice_6pack",
          "milk_carton_tall",
          "broccoli"
        ]
      ]
    },
    {
      "r": 4,
      "c": 0,
      "layers": [
        [
          "pomegranate",
          "red_onion",
          "juice_6pack"
        ],
        [
          "popsicle_twin",
          "bee_toy",
          "chocolate_tablet"
        ],
        [
          "juice_6pack",
          "juice_6pack",
          "cracker_box"
        ],
        [
          "red_onion",
          "bee_toy",
          "cracker_box"
        ]
      ]
    },
    {
      "r": 4,
      "c": 1,
      "lock": 1,
      "layers": [
        [
          "pomegranate",
          "pumpkin",
          "owl_toy"
        ],
        [
          "chocolate_tablet",
          "broccoli",
          "green_beans"
        ],
        [
          "broccoli",
          "chocolate_tablet",
          "cupcake_tray"
        ]
      ]
    },
    {
      "r": 4,
      "c": 2,
      "lock": 3,
      "layers": [
        [
          "bee_toy",
          "bee_toy",
          null
        ],
        [
          "cracker_box",
          "green_beans",
          "owl_toy"
        ],
        [
          "cracker_box",
          "bee_toy",
          "pumpkin"
        ]
      ]
    }
  ]
}
