{
  "level": 44,
  "timeLimit": 306,
  "cols": 3,
  "rows": 4,
  "cellCap": 3,
  "goods": [
    "air_freshener",
    "berry_smoothie",
    "cereal_box",
    "cotton_candy",
    "cream_cheese",
    "frozen_berries",
    "grapes",
    "gum_pack",
    "oat_canister",
    "paint_can",
    "sandwich_cookies",
    "tea_box",
    "toaster_pastry",
    "tortilla_chips"
  ],
  "combo": {
    "resetAfterMs": 20000
  },
  "scoring": {
    "starsPerSort": 1,
    "comboBonus": 1
  },
  "_gen": {
    "distinct": 14,
    "depthRange": [
      3,
      4
    ],
    "emptyCubbies": 1,
    "frontGaps": 6,
    "lockCubbies": 3,
    "totalGoods": 111,
    "attempt": 0
  },
  "cubbies": [
    {
      "r": 0,
      "c": 0,
      "lock": 1,
      "layers": [
        [
          "gum_pack",
          null,
          "tortilla_chips"
        ],
        [
          "berry_smoothie",
          "cream_cheese",
          "cotton_candy"
        ],
        [
          "tea_box",
          "grapes",
          "toaster_pastry"
        ]
      ]
    },
    {
      "r": 0,
      "c": 1,
      "lock": 4,
      "layers": [
        [
          "sandwich_cookies",
          "toaster_pastry",
          null
        ],
        [
          "cotton_candy",
          "oat_canister",
          "tortilla_chips"
        ],
        [
          "oat_canister",
          "paint_can",
          "cream_cheese"
        ],
        [
          "oat_canister",
          "frozen_berries",
          "tea_box"
        ]
      ]
    },
    {
      "r": 0,
      "c": 2,
      "layers": [
        [
          "oat_canister",
          "toaster_pastry",
          "sandwich_cookies"
        ],
        [
          "oat_canister",
          "toaster_pastry",
          "cream_cheese"
        ],
        [
          "toaster_pastry",
          "frozen_berries",
          "berry_smoothie"
        ],
        [
          "berry_smoothie",
          "gum_pack",
          "air_freshener"
        ]
      ]
    },
    {
      "r": 1,
      "c": 0,
      "layers": [
        [
          "cream_cheese",
          null,
          "grapes"
        ],
        [
          "paint_can",
          "cream_cheese",
          "air_freshener"
        ],
        [
          "cream_cheese",
          "cotton_candy",
          "berry_smoothie"
        ],
        [
          "cereal_box",
          "grapes",
          "berry_smoothie"
        ]
      ]
    },
    {
      "r": 1,
      "c": 1,
      "lock": 3,
      "layers": [
        [
          null,
          "air_freshener",
          "air_freshener"
        ],
        [
          "frozen_berries",
          "tea_box",
          "cereal_box"
        ],
        [
          "toaster_pastry",
          "cotton_candy",
          "gum_pack"
        ]
      ]
    },
    {
      "r": 1,
      "c": 2,
      "layers": [
        [
          "gum_pack",
          "air_freshener",
          "air_freshener"
        ],
        [
          "gum_pack",
          "berry_smoothie",
          "tea_box"
        ],
        [
          "cereal_box",
          "air_freshener",
          "tortilla_chips"
        ],
        [
          "tea_box",
          "toaster_pastry",
          "tortilla_chips"
        ]
      ]
    },
    {
      "r": 2,
      "c": 0,
      "layers": [
        [
          null,
          null,
          null
        ]
      ]
    },
    {
      "r": 2,
      "c": 1,
      "layers": [
        [
          "cream_cheese",
          "paint_can",
          "paint_can"
        ],
        [
          "tea_box",
          "sandwich_cookies",
          "cream_cheese"
        ],
        [
          "cotton_candy",
          "sandwich_cookies",
          "tortilla_chips"
        ],
        [
          "cereal_box",
          "berry_smoothie",
          "tortilla_chips"
        ]
      ]
    },
    {
      "r": 2,
      "c": 2,
      "layers": [
        [
          "tortilla_chips",
          "tortilla_chips",
          "tea_box"
        ],
        [
          "gum_pack",
          "frozen_berries",
          "cotton_candy"
        ],
        [
          "cereal_box",
          "cereal_box",
          "frozen_berries"
        ]
      ]
    },
    {
      "r": 3,
      "c": 0,
      "layers": [
        [
          "cream_cheese",
          "tea_box",
          "oat_canister"
        ],
        [
          "oat_canister",
          "paint_can",
          "berry_smoothie"
        ],
        [
          "tortilla_chips",
          "oat_canister",
          "grapes"
        ],
        [
          "grapes",
          "cereal_box",
          "frozen_berries"
        ]
      ]
    },
    {
      "r": 3,
      "c": 1,
      "layers": [
        [
          "sandwich_cookies",
          null,
          null
        ],
        [
          "cereal_box",
          "grapes",
          "air_freshener"
        ],
        [
          "gum_pack",
          "gum_pack",
          "paint_can"
        ]
      ]
    },
    {
      "r": 3,
      "c": 2,
      "layers": [
        [
          "tea_box",
          "toaster_pastry",
          "air_freshener"
        ],
        [
          "gum_pack",
          "berry_smoothie",
          "cereal_box"
        ],
        [
          "toaster_pastry",
          "sandwich_cookies",
          "oat_canister"
        ]
      ]
    }
  ]
}
