{
  "level": 54,
  "timeLimit": 291,
  "cols": 3,
  "rows": 4,
  "cellCap": 3,
  "goods": [
    "air_freshener",
    "berry_smoothie",
    "cereal_box",
    "choc_chip_bag",
    "cream_cheese",
    "cream_cheese_tub",
    "grapes",
    "gum_pack",
    "oat_canister",
    "paint_can",
    "rice_bag",
    "sandwich_cookies",
    "tea_box",
    "toaster_pastry"
  ],
  "combo": {
    "resetAfterMs": 20000
  },
  "scoring": {
    "starsPerSort": 1,
    "comboBonus": 1
  },
  "_gen": {
    "distinct": 14,
    "depthRange": [
      3,
      5
    ],
    "emptyCubbies": 1,
    "frontGaps": 6,
    "lockCubbies": 4,
    "totalGoods": 120,
    "attempt": 4
  },
  "cubbies": [
    {
      "r": 0,
      "c": 0,
      "lock": 2,
      "layers": [
        [
          "berry_smoothie",
          null,
          "cream_cheese_tub"
        ],
        [
          "berry_smoothie",
          "tea_box",
          "toaster_pastry"
        ],
        [
          "tea_box",
          "paint_can",
          "tea_box"
        ],
        [
          "sandwich_cookies",
          "cream_cheese_tub",
          "toaster_pastry"
        ]
      ]
    },
    {
      "r": 0,
      "c": 1,
      "layers": [
        [
          "berry_smoothie",
          "gum_pack",
          "cream_cheese"
        ],
        [
          "sandwich_cookies",
          "oat_canister",
          "paint_can"
        ],
        [
          "rice_bag",
          "cream_cheese",
          "grapes"
        ]
      ]
    },
    {
      "r": 0,
      "c": 2,
      "layers": [
        [
          "grapes",
          "gum_pack",
          "cereal_box"
        ],
        [
          "gum_pack",
          "tea_box",
          "grapes"
        ],
        [
          "berry_smoothie",
          "cream_cheese_tub",
          "air_freshener"
        ],
        [
          "toaster_pastry",
          "tea_box",
          "choc_chip_bag"
        ]
      ]
    },
    {
      "r": 1,
      "c": 0,
      "lock": 1,
      "layers": [
        [
          "gum_pack",
          "berry_smoothie",
          "oat_canister"
        ],
        [
          "paint_can",
          "air_freshener",
          "oat_canister"
        ],
        [
          "oat_canister",
          "cream_cheese_tub",
          "cream_cheese"
        ],
        [
          "toaster_pastry",
          "paint_can",
          "toaster_pastry"
        ],
        [
          "cream_cheese_tub",
          "choc_chip_bag",
          "air_freshener"
        ]
      ]
    },
    {
      "r": 1,
      "c": 1,
      "layers": [
        [
          "grapes",
          "oat_canister",
          "choc_chip_bag"
        ],
        [
          "cereal_box",
          "paint_can",
          "berry_smoothie"
        ],
        [
          "cereal_box",
          "cream_cheese",
          "rice_bag"
        ]
      ]
    },
    {
      "r": 1,
      "c": 2,
      "layers": [
        [
          "toaster_pastry",
          "berry_smoothie",
          "grapes"
        ],
        [
          "air_freshener",
          "berry_smoothie",
          "sandwich_cookies"
        ],
        [
          "oat_canister",
          "cereal_box",
          "choc_chip_bag"
        ]
      ]
    },
    {
      "r": 2,
      "c": 0,
      "layers": [
        [
          null,
          "choc_chip_bag",
          null
        ],
        [
          "sandwich_cookies",
          "cereal_box",
          "tea_box"
        ],
        [
          "cereal_box",
          "sandwich_cookies",
          "tea_box"
        ],
        [
          "cream_cheese",
          "paint_can",
          "air_freshener"
        ],
        [
          "grapes",
          "tea_box",
          "gum_pack"
        ]
      ]
    },
    {
      "r": 2,
      "c": 1,
      "layers": [
        [
          "grapes",
          "air_freshener",
          null
        ],
        [
          "oat_canister",
          "choc_chip_bag",
          "cereal_box"
        ],
        [
          "rice_bag",
          "sandwich_cookies",
          "gum_pack"
        ]
      ]
    },
    {
      "r": 2,
      "c": 2,
      "layers": [
        [
          "gum_pack",
          "cereal_box",
          "choc_chip_bag"
        ],
        [
          "berry_smoothie",
          "paint_can",
          "rice_bag"
        ],
        [
          "toaster_pastry",
          "paint_can",
          "air_freshener"
        ],
        [
          "gum_pack",
          "cream_cheese",
          "paint_can"
        ]
      ]
    },
    {
      "r": 3,
      "c": 0,
      "layers": [
        [
          null,
          null,
          null
        ]
      ]
    },
    {
      "r": 3,
      "c": 1,
      "lock": 1,
      "layers": [
        [
          "toaster_pastry",
          "air_freshener",
          null
        ],
        [
          "tea_box",
          "sandwich_cookies",
          "grapes"
        ],
        [
          "cream_cheese_tub",
          "air_freshener",
          "choc_chip_bag"
        ],
        [
          "sandwich_cookies",
          "choc_chip_bag",
          "grapes"
        ],
        [
          "cream_cheese",
          "cream_cheese",
          "sandwich_cookies"
        ]
      ]
    },
    {
      "r": 3,
      "c": 2,
      "lock": 1,
      "layers": [
        [
          null,
          "toaster_pastry",
          "cereal_box"
        ],
        [
          "oat_canister",
          "oat_canister",
          "rice_bag"
        ],
        [
          "gum_pack",
          "rice_bag",
          "cream_cheese"
        ]
      ]
    }
  ]
}
