{
  "level": 93,
  "timeLimit": 240,
  "cols": 4,
  "rows": 5,
  "cellCap": 3,
  "goods": [
    "air_freshener",
    "artichoke",
    "bell_pepper_red",
    "bunny",
    "coffee_cup",
    "gift_box",
    "gum_pack",
    "icecream_cone",
    "mayo",
    "mushroom_brown",
    "paint_can",
    "pesto_jar",
    "robot_toy",
    "seaweed_snack",
    "snack",
    "soap_dispenser"
  ],
  "combo": {
    "resetAfterMs": 20000
  },
  "scoring": {
    "starsPerSort": 1,
    "comboBonus": 1
  },
  "_gen": {
    "distinct": 16,
    "depthRange": [
      4,
      5
    ],
    "emptyCubbies": 1,
    "frontGaps": 9,
    "lockCubbies": 7,
    "totalGoods": 243,
    "attempt": 5
  },
  "cubbies": [
    {
      "r": 0,
      "c": 0,
      "lock": 4,
      "layers": [
        [
          "robot_toy",
          "mayo",
          "artichoke"
        ],
        [
          "paint_can",
          "pesto_jar",
          "gum_pack"
        ],
        [
          "soap_dispenser",
          "robot_toy",
          "paint_can"
        ],
        [
          "coffee_cup",
          "seaweed_snack",
          "air_freshener"
        ]
      ]
    },
    {
      "r": 0,
      "c": 1,
      "layers": [
        [
          null,
          null,
          null
        ]
      ]
    },
    {
      "r": 0,
      "c": 2,
      "lock": 5,
      "layers": [
        [
          "pesto_jar",
          "bunny",
          "snack"
        ],
        [
          "gift_box",
          "coffee_cup",
          "seaweed_snack"
        ],
        [
          "air_freshener",
          "coffee_cup",
          "artichoke"
        ],
        [
          "artichoke",
          "bunny",
          "snack"
        ],
        [
          "gum_pack",
          "bell_pepper_red",
          "robot_toy"
        ]
      ]
    },
    {
      "r": 0,
      "c": 3,
      "lock": 4,
      "layers": [
        [
          "gum_pack",
          "icecream_cone",
          "air_freshener"
        ],
        [
          "soap_dispenser",
          "snack",
          "seaweed_snack"
        ],
        [
          "snack",
          "mayo",
          "coffee_cup"
        ],
        [
          "bunny",
          "snack",
          "gift_box"
        ],
        [
          "mushroom_brown",
          "pesto_jar",
          "paint_can"
        ]
      ]
    },
    {
      "r": 1,
      "c": 0,
      "layers": [
        [
          "gift_box",
          "air_freshener",
          "soap_dispenser"
        ],
        [
          "bell_pepper_red",
          "seaweed_snack",
          "seaweed_snack"
        ],
        [
          "snack",
          "seaweed_snack",
          "soap_dispenser"
        ],
        [
          "mushroom_brown",
          "gum_pack",
          "artichoke"
        ],
        [
          "gift_box",
          "seaweed_snack",
          "robot_toy"
        ]
      ]
    },
    {
      "r": 1,
      "c": 1,
      "lock": 5,
      "layers": [
        [
          null,
          "pesto_jar",
          "seaweed_snack"
        ],
        [
          "snack",
          "artichoke",
          "artichoke"
        ],
        [
          "mushroom_brown",
          "snack",
          "gum_pack"
        ],
        [
          "bell_pepper_red",
          "snack",
          "bell_pepper_red"
        ]
      ]
    },
    {
      "r": 1,
      "c": 2,
      "layers": [
        [
          "artichoke",
          "mushroom_brown",
          "air_freshener"
        ],
        [
          "gift_box",
          "gift_box",
          "soap_dispenser"
        ],
        [
          "gum_pack",
          "icecream_cone",
          "gift_box"
        ],
        [
          "bell_pepper_red",
          "artichoke",
          "air_freshener"
        ],
        [
          "icecream_cone",
          "bunny",
          "robot_toy"
        ]
      ]
    },
    {
      "r": 1,
      "c": 3,
      "layers": [
        [
          "robot_toy",
          "paint_can",
          "paint_can"
        ],
        [
          "air_freshener",
          "bunny",
          "icecream_cone"
        ],
        [
          "mayo",
          "artichoke",
          "soap_dispenser"
        ],
        [
          "gum_pack",
          "gum_pack",
          "mushroom_brown"
        ]
      ]
    },
    {
      "r": 2,
      "c": 0,
      "layers": [
        [
          "soap_dispenser",
          "pesto_jar",
          "gift_box"
        ],
        [
          "soap_dispenser",
          "bunny",
          "gift_box"
        ],
        [
          "pesto_jar",
          "paint_can",
          "bunny"
        ],
        [
          "air_freshener",
          "mushroom_brown",
          "icecream_cone"
        ]
      ]
    },
    {
      "r": 2,
      "c": 1,
      "layers": [
        [
          "mayo",
          "mayo",
          "mayo"
        ],
        [
          "icecream_cone",
          "soap_dispenser",
          "snack"
        ],
        [
          "icecream_cone",
          "seaweed_snack",
          "bell_pepper_red"
        ],
        [
          "mayo",
          "robot_toy",
          "bell_pepper_red"
        ]
      ]
    },
    {
      "r": 2,
      "c": 2,
      "layers": [
        [
          "soap_dispenser",
          null,
          "soap_dispenser"
        ],
        [
          "seaweed_snack",
          "air_freshener",
          "mushroom_brown"
        ],
        [
          "bell_pepper_red",
          "air_freshener",
          "gift_box"
        ],
        [
          "air_freshener",
          "gift_box",
          "mushroom_brown"
        ],
        [
          "soap_dispenser",
          "artichoke",
          "coffee_cup"
        ]
      ]
    },
    {
      "r": 2,
      "c": 3,
      "layers": [
        [
          null,
          "bunny",
          "paint_can"
        ],
        [
          "mayo",
          "pesto_jar",
          "mayo"
        ],
        [
          "paint_can",
          "gift_box",
          "gift_box"
        ],
        [
          "mushroom_brown",
          "robot_toy",
          "pesto_jar"
        ],
        [
          "paint_can",
          "artichoke",
          "snack"
        ]
      ]
    },
    {
      "r": 3,
      "c": 0,
      "lock": 2,
      "layers": [
        [
          null,
          "mushroom_brown",
          "bunny"
        ],
        [
          "mayo",
          "bunny",
          "robot_toy"
        ],
        [
          "seaweed_snack",
          "bell_pepper_red",
          "pesto_jar"
        ],
        [
          "pesto_jar",
          "coffee_cup",
          "mushroom_brown"
        ]
      ]
    },
    {
      "r": 3,
      "c": 1,
      "layers": [
        [
          "air_freshener",
          "gift_box",
          "bell_pepper_red"
        ],
        [
          "icecream_cone",
          "artichoke",
          "artichoke"
        ],
        [
          "seaweed_snack",
          "air_freshener",
          "icecream_cone"
        ],
        [
          "paint_can",
          "paint_can",
          "gum_pack"
        ],
        [
          "artichoke",
          "robot_toy",
          "bell_pepper_red"
        ]
      ]
    },
    {
      "r": 3,
      "c": 2,
      "layers": [
        [
          "bunny",
          "gum_pack",
          "icecream_cone"
        ],
        [
          "snack",
          "paint_can",
          "air_freshener"
        ],
        [
          "coffee_cup",
          "mayo",
          "coffee_cup"
        ],
        [
          "mayo",
          "bell_pepper_red",
          "artichoke"
        ]
      ]
    },
    {
      "r": 3,
      "c": 3,
      "lock": 4,
      "layers": [
        [
          "snack",
          null,
          null
        ],
        [
          "robot_toy",
          "coffee_cup",
          "pesto_jar"
        ],
        [
          "soap_dispenser",
          "coffee_cup",
          "icecream_cone"
        ],
        [
          "coffee_cup",
          "robot_toy",
          "seaweed_snack"
        ]
      ]
    },
    {
      "r": 4,
      "c": 0,
      "layers": [
        [
          "snack",
          "seaweed_snack",
          null
        ],
        [
          "mayo",
          "gum_pack",
          "bunny"
        ],
        [
          "robot_toy",
          "paint_can",
          "artichoke"
        ],
        [
          "coffee_cup",
          "icecream_cone",
          "pesto_jar"
        ]
      ]
    },
    {
      "r": 4,
      "c": 1,
      "lock": 1,
      "layers": [
        [
          "mushroom_brown",
          null,
          "robot_toy"
        ],
        [
          "icecream_cone",
          "gift_box",
          "coffee_cup"
        ],
        [
          "seaweed_snack",
          "pesto_jar",
          "soap_dispenser"
        ],
        [
          "paint_can",
          "pesto_jar",
          "icecream_cone"
        ]
      ]
    },
    {
      "r": 4,
      "c": 2,
      "layers": [
        [
          "paint_can",
          "mushroom_brown",
          null
        ],
        [
          "gum_pack",
          "pesto_jar",
          "coffee_cup"
        ],
        [
          "mushroom_brown",
          "air_freshener",
          "gum_pack"
        ],
        [
          "robot_toy",
          "mayo",
          "bunny"
        ],
        [
          "bell_pepper_red",
          "bunny",
          "snack"
        ]
      ]
    },
    {
      "r": 4,
      "c": 3,
      "layers": [
        [
          "bunny",
          "icecream_cone",
          "artichoke"
        ],
        [
          "gum_pack",
          "coffee_cup",
          "mayo"
        ],
        [
          "bell_pepper_red",
          "bell_pepper_red",
          "gum_pack"
        ],
        [
          "soap_dispenser",
          "artichoke",
          "mushroom_brown"
        ]
      ]
    }
  ]
}
