{
  "level": 47,
  "timeLimit": 540,
  "cols": 3,
  "rows": 5,
  "cellCap": 3,
  "goods": [
    "beet",
    "broccoli",
    "candy_jar",
    "cereal_box_blue",
    "cookie_disc",
    "detergent",
    "fox_toy",
    "frozen_berries",
    "glass_cleaner",
    "grape_soda",
    "green_tea",
    "mustard",
    "owl_toy",
    "pringle_purple",
    "red_onion",
    "tennis_can"
  ],
  "combo": {
    "resetAfterMs": 20000
  },
  "scoring": {
    "starsPerSort": 1,
    "comboBonus": 1
  },
  "_gen": {
    "distinct": 16,
    "depthRange": [
      1,
      5
    ],
    "deepN": 2,
    "emptyCubbies": 1,
    "frontGaps": 9,
    "lockCubbies": 2,
    "totalGoods": 84,
    "attempt": 4
  },
  "cubbies": [
    {
      "r": 0,
      "c": 0,
      "layers": [
        [
          "mustard",
          "red_onion",
          "tennis_can"
        ],
        [
          "broccoli",
          "mustard",
          "owl_toy"
        ],
        [
          "broccoli",
          "mustard",
          "red_onion"
        ],
        [
          "broccoli",
          "beet",
          "owl_toy"
        ],
        [
          "owl_toy",
          "tennis_can",
          "glass_cleaner"
        ]
      ]
    },
    {
      "r": 0,
      "c": 1,
      "layers": [
        [
          "pringle_purple",
          "grape_soda",
          null
        ],
        [
          "detergent",
          "red_onion",
          "red_onion"
        ],
        [
          "tennis_can",
          "pringle_purple",
          "glass_cleaner"
        ],
        [
          "glass_cleaner",
          "fox_toy",
          "grape_soda"
        ],
        [
          "beet",
          "owl_toy",
          "green_tea"
        ]
      ]
    },
    {
      "r": 0,
      "c": 2,
      "layers": [
        [
          null,
          "pringle_purple",
          "fox_toy"
        ]
      ]
    },
    {
      "r": 1,
      "c": 0,
      "lock": 1,
      "layers": [
        [
          null,
          "frozen_berries",
          "frozen_berries"
        ],
        [
          "cereal_box_blue",
          "candy_jar",
          "beet"
        ]
      ]
    },
    {
      "r": 1,
      "c": 1,
      "layers": [
        [
          "candy_jar",
          "fox_toy",
          null
        ],
        [
          "detergent",
          "fox_toy",
          "grape_soda"
        ],
        [
          "mustard",
          "cereal_box_blue",
          "detergent"
        ]
      ]
    },
    {
      "r": 1,
      "c": 2,
      "layers": [
        [
          "fox_toy",
          "glass_cleaner",
          "tennis_can"
        ]
      ]
    },
    {
      "r": 2,
      "c": 0,
      "layers": [
        [
          "green_tea",
          null,
          null
        ]
      ]
    },
    {
      "r": 2,
      "c": 1,
      "layers": [
        [
          "cereal_box_blue",
          "cereal_box_blue",
          "detergent"
        ],
        [
          "mustard",
          "detergent",
          "beet"
        ]
      ]
    },
    {
      "r": 2,
      "c": 2,
      "layers": [
        [
          "glass_cleaner",
          "cookie_disc",
          "frozen_berries"
        ]
      ]
    },
    {
      "r": 3,
      "c": 0,
      "layers": [
        [
          "cereal_box_blue",
          "detergent",
          null
        ],
        [
          "candy_jar",
          "cookie_disc",
          "grape_soda"
        ]
      ]
    },
    {
      "r": 3,
      "c": 1,
      "layers": [
        [
          "fox_toy",
          "beet",
          "candy_jar"
        ],
        [
          "mustard",
          "candy_jar",
          "tennis_can"
        ]
      ]
    },
    {
      "r": 3,
      "c": 2,
      "layers": [
        [
          "grape_soda",
          "red_onion",
          "owl_toy"
        ],
        [
          "grape_soda",
          "cookie_disc",
          "red_onion"
        ]
      ]
    },
    {
      "r": 4,
      "c": 0,
      "lock": 3,
      "layers": [
        [
          "candy_jar",
          null,
          null
        ],
        [
          "glass_cleaner",
          "owl_toy",
          "broccoli"
        ],
        [
          "cereal_box_blue",
          "green_tea",
          "broccoli"
        ]
      ]
    },
    {
      "r": 4,
      "c": 1,
      "layers": [
        [
          "beet",
          "tennis_can",
          "broccoli"
        ]
      ]
    },
    {
      "r": 4,
      "c": 2,
      "layers": [
        [
          null,
          null,
          null
        ]
      ]
    }
  ]
}
