{
  "level": 90,
  "timeLimit": 335,
  "cols": 4,
  "rows": 5,
  "cellCap": 3,
  "goods": [
    "air_freshener",
    "berry_smoothie",
    "butter_box",
    "cereal_box",
    "cereal_choco",
    "cream_cheese",
    "frozen_berries",
    "grapes",
    "gum_pack",
    "paint_can",
    "rice_bag",
    "sandwich_cookies",
    "spray_cleaner",
    "tea_box",
    "toaster_pastry"
  ],
  "combo": {
    "resetAfterMs": 20000
  },
  "scoring": {
    "starsPerSort": 1,
    "comboBonus": 1
  },
  "_gen": {
    "distinct": 15,
    "depthRange": [
      4,
      5
    ],
    "emptyCubbies": 1,
    "frontGaps": 12,
    "lockCubbies": 7,
    "totalGoods": 243,
    "attempt": 65
  },
  "cubbies": [
    {
      "r": 0,
      "c": 0,
      "lock": 3,
      "layers": [
        [
          "butter_box",
          "paint_can",
          "rice_bag"
        ],
        [
          "butter_box",
          "berry_smoothie",
          "butter_box"
        ],
        [
          "berry_smoothie",
          "sandwich_cookies",
          "paint_can"
        ],
        [
          "toaster_pastry",
          "spray_cleaner",
          "cereal_choco"
        ]
      ]
    },
    {
      "r": 0,
      "c": 1,
      "lock": 2,
      "layers": [
        [
          "tea_box",
          "spray_cleaner",
          "tea_box"
        ],
        [
          "sandwich_cookies",
          "toaster_pastry",
          "butter_box"
        ],
        [
          "grapes",
          "air_freshener",
          "grapes"
        ],
        [
          "gum_pack",
          "toaster_pastry",
          "cereal_choco"
        ]
      ]
    },
    {
      "r": 0,
      "c": 2,
      "lock": 5,
      "layers": [
        [
          null,
          "frozen_berries",
          "rice_bag"
        ],
        [
          "gum_pack",
          "cereal_box",
          "cereal_choco"
        ],
        [
          "gum_pack",
          "rice_bag",
          "tea_box"
        ],
        [
          "spray_cleaner",
          "butter_box",
          "toaster_pastry"
        ],
        [
          "toaster_pastry",
          "berry_smoothie",
          "berry_smoothie"
        ]
      ]
    },
    {
      "r": 0,
      "c": 3,
      "lock": 1,
      "layers": [
        [
          null,
          "cream_cheese",
          "gum_pack"
        ],
        [
          "cream_cheese",
          "frozen_berries",
          "cereal_box"
        ],
        [
          "rice_bag",
          "sandwich_cookies",
          "paint_can"
        ],
        [
          "cream_cheese",
          "grapes",
          "air_freshener"
        ]
      ]
    },
    {
      "r": 1,
      "c": 0,
      "layers": [
        [
          null,
          "sandwich_cookies",
          "toaster_pastry"
        ],
        [
          "frozen_berries",
          "spray_cleaner",
          "rice_bag"
        ],
        [
          "tea_box",
          "gum_pack",
          "paint_can"
        ],
        [
          "gum_pack",
          "toaster_pastry",
          "paint_can"
        ]
      ]
    },
    {
      "r": 1,
      "c": 1,
      "layers": [
        [
          "cereal_box",
          "frozen_berries",
          "air_freshener"
        ],
        [
          "sandwich_cookies",
          "cream_cheese",
          "paint_can"
        ],
        [
          "grapes",
          "spray_cleaner",
          "cereal_choco"
        ],
        [
          "rice_bag",
          "tea_box",
          "gum_pack"
        ],
        [
          "paint_can",
          "cereal_choco",
          "sandwich_cookies"
        ]
      ]
    },
    {
      "r": 1,
      "c": 2,
      "layers": [
        [
          null,
          "tea_box",
          "paint_can"
        ],
        [
          "toaster_pastry",
          "paint_can",
          "air_freshener"
        ],
        [
          "cream_cheese",
          "cereal_choco",
          "sandwich_cookies"
        ],
        [
          "spray_cleaner",
          "paint_can",
          "cereal_box"
        ]
      ]
    },
    {
      "r": 1,
      "c": 3,
      "layers": [
        [
          "berry_smoothie",
          "butter_box",
          "spray_cleaner"
        ],
        [
          "paint_can",
          "cereal_choco",
          "tea_box"
        ],
        [
          "spray_cleaner",
          "air_freshener",
          "cereal_box"
        ],
        [
          "rice_bag",
          "cereal_box",
          "cereal_choco"
        ],
        [
          "gum_pack",
          "grapes",
          "grapes"
        ]
      ]
    },
    {
      "r": 2,
      "c": 0,
      "lock": 4,
      "layers": [
        [
          "butter_box",
          "spray_cleaner",
          "paint_can"
        ],
        [
          "air_freshener",
          "frozen_berries",
          "berry_smoothie"
        ],
        [
          "butter_box",
          "berry_smoothie",
          "grapes"
        ],
        [
          "grapes",
          "tea_box",
          "frozen_berries"
        ]
      ]
    },
    {
      "r": 2,
      "c": 1,
      "layers": [
        [
          "gum_pack",
          "tea_box",
          null
        ],
        [
          "tea_box",
          "grapes",
          "cereal_box"
        ],
        [
          "paint_can",
          "cereal_choco",
          "frozen_berries"
        ],
        [
          "spray_cleaner",
          "sandwich_cookies",
          "butter_box"
        ]
      ]
    },
    {
      "r": 2,
      "c": 2,
      "layers": [
        [
          null,
          "cereal_choco",
          "frozen_berries"
        ],
        [
          "frozen_berries",
          "butter_box",
          "butter_box"
        ],
        [
          "berry_smoothie",
          "tea_box",
          "tea_box"
        ],
        [
          "air_freshener",
          "gum_pack",
          "paint_can"
        ],
        [
          "cereal_choco",
          "cream_cheese",
          "gum_pack"
        ]
      ]
    },
    {
      "r": 2,
      "c": 3,
      "layers": [
        [
          "frozen_berries",
          "gum_pack",
          "tea_box"
        ],
        [
          "frozen_berries",
          "cereal_choco",
          "berry_smoothie"
        ],
        [
          "gum_pack",
          "sandwich_cookies",
          "tea_box"
        ],
        [
          "gum_pack",
          "cereal_box",
          "paint_can"
        ],
        [
          "frozen_berries",
          "cream_cheese",
          "sandwich_cookies"
        ]
      ]
    },
    {
      "r": 3,
      "c": 0,
      "lock": 3,
      "layers": [
        [
          null,
          "tea_box",
          "cereal_choco"
        ],
        [
          "cereal_choco",
          "berry_smoothie",
          "air_freshener"
        ],
        [
          "rice_bag",
          "tea_box",
          "frozen_berries"
        ],
        [
          "cream_cheese",
          "sandwich_cookies",
          "rice_bag"
        ],
        [
          "cereal_box",
          "spray_cleaner",
          "air_freshener"
        ]
      ]
    },
    {
      "r": 3,
      "c": 1,
      "layers": [
        [
          "sandwich_cookies",
          null,
          "spray_cleaner"
        ],
        [
          "berry_smoothie",
          "toaster_pastry",
          "toaster_pastry"
        ],
        [
          "butter_box",
          "cereal_box",
          "tea_box"
        ],
        [
          "grapes",
          "paint_can",
          "toaster_pastry"
        ]
      ]
    },
    {
      "r": 3,
      "c": 2,
      "layers": [
        [
          "air_freshener",
          "rice_bag",
          "grapes"
        ],
        [
          "air_freshener",
          "butter_box",
          "toaster_pastry"
        ],
        [
          "gum_pack",
          "cereal_box",
          "sandwich_cookies"
        ],
        [
          "spray_cleaner",
          "cream_cheese",
          "cream_cheese"
        ]
      ]
    },
    {
      "r": 3,
      "c": 3,
      "layers": [
        [
          "paint_can",
          null,
          "rice_bag"
        ],
        [
          "toaster_pastry",
          "frozen_berries",
          "spray_cleaner"
        ],
        [
          "cream_cheese",
          "cereal_box",
          "frozen_berries"
        ],
        [
          "toaster_pastry",
          "spray_cleaner",
          "air_freshener"
        ],
        [
          "cereal_box",
          "grapes",
          "sandwich_cookies"
        ]
      ]
    },
    {
      "r": 4,
      "c": 0,
      "lock": 4,
      "layers": [
        [
          "butter_box",
          null,
          "cream_cheese"
        ],
        [
          "berry_smoothie",
          "rice_bag",
          "butter_box"
        ],
        [
          "toaster_pastry",
          "grapes",
          "sandwich_cookies"
        ],
        [
          "cereal_box",
          "rice_bag",
          "cream_cheese"
        ],
        [
          "tea_box",
          "berry_smoothie",
          "berry_smoothie"
        ]
      ]
    },
    {
      "r": 4,
      "c": 1,
      "layers": [
        [
          "air_freshener",
          "frozen_berries",
          null
        ],
        [
          "spray_cleaner",
          "rice_bag",
          "gum_pack"
        ],
        [
          "rice_bag",
          "grapes",
          "butter_box"
        ],
        [
          "spray_cleaner",
          "grapes",
          "cereal_choco"
        ]
      ]
    },
    {
      "r": 4,
      "c": 2,
      "layers": [
        [
          null,
          null,
          null
        ]
      ]
    },
    {
      "r": 4,
      "c": 3,
      "layers": [
        [
          null,
          "air_freshener",
          "butter_box"
        ],
        [
          "gum_pack",
          "frozen_berries",
          "paint_can"
        ],
        [
          "frozen_berries",
          "butter_box",
          "berry_smoothie"
        ],
        [
          "cream_cheese",
          "gum_pack",
          "cream_cheese"
        ],
        [
          "spray_cleaner",
          "air_freshener",
          "cereal_box"
        ]
      ]
    }
  ]
}
