{
  "level": 4,
  "timeLimit": 360,
  "cols": 3,
  "rows": 4,
  "cellCap": 3,
  "goods": [
    "butter_box",
    "chips",
    "cream_cheese",
    "grapes",
    "gum_pack",
    "mayo_squeeze",
    "plum",
    "rice_bag",
    "sandwich_cookies",
    "seaweed_snack",
    "tea_box",
    "toaster_pastry"
  ],
  "combo": {
    "resetAfterMs": 20000
  },
  "scoring": {
    "starsPerSort": 1,
    "comboBonus": 1
  },
  "_gen": {
    "distinct": 12,
    "depthRange": [
      1,
      2
    ],
    "emptyCubbies": 1,
    "frontGaps": 6,
    "lockCubbies": 0,
    "totalGoods": 42,
    "attempt": 0
  },
  "cubbies": [
    {
      "r": 0,
      "c": 0,
      "layers": [
        [
          "gum_pack",
          "grapes",
          "chips"
        ]
      ]
    },
    {
      "r": 0,
      "c": 1,
      "layers": [
        [
          "cream_cheese",
          null,
          "gum_pack"
        ],
        [
          "sandwich_cookies",
          "grapes",
          "mayo_squeeze"
        ]
      ]
    },
    {
      "r": 0,
      "c": 2,
      "layers": [
        [
          "toaster_pastry",
          "butter_box",
          null
        ]
      ]
    },
    {
      "r": 1,
      "c": 0,
      "layers": [
        [
          "plum",
          null,
          null
        ],
        [
          "butter_box",
          "sandwich_cookies",
          "tea_box"
        ]
      ]
    },
    {
      "r": 1,
      "c": 1,
      "layers": [
        [
          "cream_cheese",
          null,
          "gum_pack"
        ]
      ]
    },
    {
      "r": 1,
      "c": 2,
      "layers": [
        [
          "seaweed_snack",
          "mayo_squeeze",
          "grapes"
        ],
        [
          "tea_box",
          "butter_box",
          "butter_box"
        ]
      ]
    },
    {
      "r": 2,
      "c": 0,
      "layers": [
        [
          "butter_box",
          "chips",
          "chips"
        ],
        [
          "toaster_pastry",
          "sandwich_cookies",
          "chips"
        ]
      ]
    },
    {
      "r": 2,
      "c": 1,
      "layers": [
        [
          null,
          null,
          null
        ]
      ]
    },
    {
      "r": 2,
      "c": 2,
      "layers": [
        [
          "rice_bag",
          "cream_cheese",
          "chips"
        ]
      ]
    },
    {
      "r": 3,
      "c": 0,
      "layers": [
        [
          "chips",
          "mayo_squeeze",
          "tea_box"
        ],
        [
          "butter_box",
          "toaster_pastry",
          "rice_bag"
        ]
      ]
    },
    {
      "r": 3,
      "c": 1,
      "layers": [
        [
          "plum",
          "seaweed_snack",
          "seaweed_snack"
        ]
      ]
    },
    {
      "r": 3,
      "c": 2,
      "layers": [
        [
          null,
          "plum",
          "rice_bag"
        ]
      ]
    }
  ]
}
