{
  "level": 34,
  "timeLimit": 320,
  "cols": 3,
  "rows": 4,
  "cellCap": 3,
  "goods": [
    "avocado",
    "cake_roll_pink",
    "cookie_tin_round",
    "corn",
    "icecream_cone",
    "jelly_bag",
    "mustard",
    "octopus_toy",
    "persimmon",
    "sheep_toy",
    "sub_sandwich",
    "teapot",
    "yogurt_4pack"
  ],
  "combo": {
    "resetAfterMs": 20000
  },
  "scoring": {
    "starsPerSort": 1,
    "comboBonus": 1
  },
  "_gen": {
    "distinct": 13,
    "depthRange": [
      3,
      4
    ],
    "workspaces": 3,
    "lockCubbies": 3,
    "totalGoods": 96,
    "attempt": 7
  },
  "cubbies": [
    {
      "r": 0,
      "c": 0,
      "lock": 3,
      "layers": [
        [
          "sheep_toy",
          "octopus_toy",
          "cake_roll_pink"
        ],
        [
          "teapot",
          "mustard",
          "sheep_toy"
        ],
        [
          "avocado",
          "persimmon",
          "octopus_toy"
        ]
      ]
    },
    {
      "r": 0,
      "c": 1,
      "lock": 1,
      "layers": [
        [
          "sheep_toy",
          "cookie_tin_round",
          "corn"
        ],
        [
          "icecream_cone",
          "icecream_cone",
          "sub_sandwich"
        ],
        [
          "jelly_bag",
          "mustard",
          "corn"
        ],
        [
          "teapot",
          "cake_roll_pink",
          "avocado"
        ]
      ]
    },
    {
      "r": 0,
      "c": 2,
      "lock": 3,
      "layers": [
        [
          "octopus_toy",
          "avocado",
          "sub_sandwich"
        ],
        [
          "jelly_bag",
          "avocado",
          "mustard"
        ],
        [
          "icecream_cone",
          "yogurt_4pack",
          "sheep_toy"
        ],
        [
          "jelly_bag",
          "jelly_bag",
          "octopus_toy"
        ]
      ]
    },
    {
      "r": 1,
      "c": 0,
      "layers": [
        [
          "cake_roll_pink",
          "cookie_tin_round",
          "persimmon"
        ],
        [
          "cookie_tin_round",
          "icecream_cone",
          "yogurt_4pack"
        ],
        [
          "sub_sandwich",
          "icecream_cone",
          "jelly_bag"
        ],
        [
          "sub_sandwich",
          "avocado",
          "jelly_bag"
        ]
      ]
    },
    {
      "r": 1,
      "c": 1,
      "layers": [
        [
          "jelly_bag",
          "jelly_bag",
          "mustard"
        ],
        [
          "mustard",
          "teapot",
          "avocado"
        ],
        [
          "cookie_tin_round",
          "cookie_tin_round",
          "cookie_tin_round"
        ],
        [
          "corn",
          "octopus_toy",
          "icecream_cone"
        ]
      ]
    },
    {
      "r": 1,
      "c": 2,
      "layers": [
        [
          "jelly_bag",
          "persimmon",
          "cookie_tin_round"
        ],
        [
          "yogurt_4pack",
          "cookie_tin_round",
          "icecream_cone"
        ],
        [
          "sheep_toy",
          "yogurt_4pack",
          "cake_roll_pink"
        ]
      ]
    },
    {
      "r": 2,
      "c": 0,
      "layers": [
        [
          "icecream_cone",
          "persimmon",
          "cookie_tin_round"
        ],
        [
          "corn",
          "yogurt_4pack",
          "sheep_toy"
        ],
        [
          "teapot",
          "cake_roll_pink",
          "cake_roll_pink"
        ],
        [
          "yogurt_4pack",
          "mustard",
          "corn"
        ]
      ]
    },
    {
      "r": 2,
      "c": 1,
      "layers": [
        [
          null,
          null,
          null
        ]
      ]
    },
    {
      "r": 2,
      "c": 2,
      "layers": [
        [
          null,
          null,
          null
        ]
      ]
    },
    {
      "r": 3,
      "c": 0,
      "layers": [
        [
          "yogurt_4pack",
          "yogurt_4pack",
          "teapot"
        ],
        [
          "persimmon",
          "sub_sandwich",
          "teapot"
        ],
        [
          "sheep_toy",
          "teapot",
          "teapot"
        ]
      ]
    },
    {
      "r": 3,
      "c": 1,
      "layers": [
        [
          null,
          null,
          null
        ]
      ]
    },
    {
      "r": 3,
      "c": 2,
      "layers": [
        [
          "teapot",
          "corn",
          "octopus_toy"
        ],
        [
          "persimmon",
          "yogurt_4pack",
          "sub_sandwich"
        ],
        [
          "sheep_toy",
          "sheep_toy",
          "icecream_cone"
        ]
      ]
    }
  ]
}
