{
  "level": 89,
  "timeLimit": 540,
  "cols": 4,
  "rows": 5,
  "cellCap": 3,
  "goods": [
    "air_freshener",
    "cabbage",
    "candy_jar",
    "cream_cheese",
    "cream_cheese_tub",
    "dish_soap",
    "dragon_toy",
    "gift_box",
    "gingerbread",
    "gum_pack",
    "hot_sauce",
    "pasta_jar_tall",
    "pomegranate",
    "pumpkin",
    "rice_bag",
    "sports_drink",
    "tea_box",
    "vinegar"
  ],
  "combo": {
    "resetAfterMs": 20000
  },
  "scoring": {
    "starsPerSort": 1,
    "comboBonus": 1
  },
  "_gen": {
    "distinct": 18,
    "depthRange": [
      1,
      7
    ],
    "deepN": 4,
    "emptyCubbies": 1,
    "frontGaps": 21,
    "lockCubbies": 6,
    "totalGoods": 108,
    "attempt": 91
  },
  "cubbies": [
    {
      "r": 0,
      "c": 0,
      "layers": [
        [
          null,
          null,
          "rice_bag"
        ],
        [
          "dragon_toy",
          "sports_drink",
          "tea_box"
        ]
      ]
    },
    {
      "r": 0,
      "c": 1,
      "layers": [
        [
          "gingerbread",
          null,
          null
        ],
        [
          "pasta_jar_tall",
          "rice_bag",
          "dragon_toy"
        ]
      ]
    },
    {
      "r": 0,
      "c": 2,
      "lock": 1,
      "layers": [
        [
          "vinegar",
          "gingerbread",
          null
        ],
        [
          "cabbage",
          "hot_sauce",
          "pasta_jar_tall"
        ],
        [
          "candy_jar",
          "hot_sauce",
          "tea_box"
        ],
        [
          "vinegar",
          "vinegar",
          "pomegranate"
        ]
      ]
    },
    {
      "r": 0,
      "c": 3,
      "layers": [
        [
          "cream_cheese_tub",
          "rice_bag",
          "rice_bag"
        ]
      ]
    },
    {
      "r": 1,
      "c": 0,
      "layers": [
        [
          "cream_cheese",
          null,
          null
        ],
        [
          "hot_sauce",
          "pomegranate",
          "air_freshener"
        ]
      ]
    },
    {
      "r": 1,
      "c": 1,
      "layers": [
        [
          "tea_box",
          "candy_jar",
          "sports_drink"
        ]
      ]
    },
    {
      "r": 1,
      "c": 2,
      "layers": [
        [
          "dish_soap",
          "gingerbread",
          "cream_cheese_tub"
        ],
        [
          "cream_cheese_tub",
          "pumpkin",
          "sports_drink"
        ],
        [
          "cream_cheese",
          "cream_cheese_tub",
          "sports_drink"
        ],
        [
          "air_freshener",
          "dish_soap",
          "vinegar"
        ],
        [
          "pomegranate",
          "vinegar",
          "pumpkin"
        ],
        [
          "candy_jar",
          "candy_jar",
          "pasta_jar_tall"
        ],
        [
          "vinegar",
          "cabbage",
          "sports_drink"
        ]
      ]
    },
    {
      "r": 1,
      "c": 3,
      "lock": 2,
      "layers": [
        [
          "hot_sauce",
          "dish_soap",
          "pumpkin"
        ],
        [
          "gum_pack",
          "pomegranate",
          "pasta_jar_tall"
        ],
        [
          "gift_box",
          "pasta_jar_tall",
          "pomegranate"
        ],
        [
          "candy_jar",
          "gift_box",
          "dragon_toy"
        ]
      ]
    },
    {
      "r": 2,
      "c": 0,
      "layers": [
        [
          null,
          null,
          null
        ]
      ]
    },
    {
      "r": 2,
      "c": 1,
      "layers": [
        [
          null,
          "dish_soap",
          null
        ],
        [
          "pomegranate",
          "tea_box",
          "cabbage"
        ]
      ]
    },
    {
      "r": 2,
      "c": 2,
      "lock": 4,
      "layers": [
        [
          "gift_box",
          null,
          "gift_box"
        ]
      ]
    },
    {
      "r": 2,
      "c": 3,
      "layers": [
        [
          null,
          "cabbage",
          "hot_sauce"
        ],
        [
          "candy_jar",
          "dragon_toy",
          "cream_cheese_tub"
        ]
      ]
    },
    {
      "r": 3,
      "c": 0,
      "layers": [
        [
          "dragon_toy",
          "pumpkin",
          "pasta_jar_tall"
        ],
        [
          "rice_bag",
          "air_freshener",
          "cabbage"
        ]
      ]
    },
    {
      "r": 3,
      "c": 1,
      "layers": [
        [
          "cream_cheese",
          "dish_soap",
          "gum_pack"
        ]
      ]
    },
    {
      "r": 3,
      "c": 2,
      "layers": [
        [
          null,
          null,
          "gum_pack"
        ],
        [
          "air_freshener",
          "gift_box",
          "gingerbread"
        ],
        [
          "rice_bag",
          "air_freshener",
          "cabbage"
        ],
        [
          "gift_box",
          "pumpkin",
          "sports_drink"
        ],
        [
          "gum_pack",
          "gingerbread",
          "dish_soap"
        ]
      ]
    },
    {
      "r": 3,
      "c": 3,
      "lock": 5,
      "layers": [
        [
          "cream_cheese_tub",
          null,
          null
        ]
      ]
    },
    {
      "r": 4,
      "c": 0,
      "lock": 4,
      "layers": [
        [
          null,
          "dragon_toy",
          null
        ],
        [
          "pumpkin",
          "tea_box",
          "hot_sauce"
        ]
      ]
    },
    {
      "r": 4,
      "c": 1,
      "layers": [
        [
          "cream_cheese",
          null,
          null
        ]
      ]
    },
    {
      "r": 4,
      "c": 2,
      "lock": 5,
      "layers": [
        [
          "gingerbread",
          null,
          "gum_pack"
        ]
      ]
    },
    {
      "r": 4,
      "c": 3,
      "layers": [
        [
          null,
          "tea_box",
          "gum_pack"
        ],
        [
          "air_freshener",
          "cream_cheese",
          "cream_cheese"
        ]
      ]
    }
  ]
}
